Metadata-Version: 2.4
Name: domaintools_api
Version: 2.6.1
Summary: DomainTools Official Python API
Author-email: DomainTools <integrations@domaintools.com>
License: The MIT License (MIT)
Project-URL: Homepage, https://github.com/domaintools/python_api
Keywords: Python,Python3
Classifier: Development Status :: 5 - Production/Stable
Classifier: Intended Audience :: Developers
Classifier: Natural Language :: English
Classifier: Environment :: Console
Classifier: License :: OSI Approved :: MIT License
Classifier: Programming Language :: Python
Classifier: Programming Language :: Python :: 3.9
Classifier: Programming Language :: Python :: 3.10
Classifier: Topic :: Software Development :: Libraries
Classifier: Topic :: Utilities
Requires-Python: >=3.9
License-File: LICENSE
Requires-Dist: httpx==0.28.1
Requires-Dist: rich
Requires-Dist: typer
Provides-Extra: test
Requires-Dist: pytest; extra == "test"
Requires-Dist: mock; extra == "test"
Dynamic: license-file
